tinyms/__init__.py
tinyms/callbacks.py
tinyms/common.py
tinyms/context.py
tinyms/initializers.py
tinyms/layers.py
tinyms/losses.py
tinyms/metrics.py
tinyms/primitives.py
tinyms/version.py
tinyms/app/__init__.py
tinyms/app/object_detection/__init__.py
tinyms/app/object_detection/object_detector.py
tinyms/app/object_detection/utils/__init__.py
tinyms/app/object_detection/utils/config_util.py
tinyms/app/object_detection/utils/view_util.py
tinyms/data/__init__.py
tinyms/data/converter.py
tinyms/data/loader.py
tinyms/data/utils.py
tinyms/hub/__init__.py
tinyms/hub/hubconf.py
tinyms/hub/load.py
tinyms/hub/assets/tinyms/0.2/alexnet_v1_cifar10.yaml
tinyms/hub/assets/tinyms/0.2/lenet5_v1_mnist.yaml
tinyms/hub/assets/tinyms/0.2/mobilenet_v2_cifar10.yaml
tinyms/hub/assets/tinyms/0.2/resnet50_v1_cifar10.yaml
tinyms/hub/assets/tinyms/0.2/resnet50_v1_mushroom.yaml
tinyms/hub/assets/tinyms/0.2/ssd300_v1_voc2007.yaml
tinyms/hub/assets/tinyms/0.2/vgg16_v1_cifar10.yaml
tinyms/hub/utils/__init__.py
tinyms/hub/utils/check.py
tinyms/hub/utils/download.py
tinyms/model/__init__.py
tinyms/model/alexnet.py
tinyms/model/densenet100.py
tinyms/model/lenet5.py
tinyms/model/mobilenetv2.py
tinyms/model/resnet50.py
tinyms/model/sentimentnet.py
tinyms/model/ssd300.py
tinyms/model/vgg.py
tinyms/model/bert/__init__.py
tinyms/model/bert/bert.py
tinyms/model/bert/bert_for_finetune.py
tinyms/model/bert/bert_for_pretraining.py
tinyms/model/bert/finetune_eval_model.py
tinyms/model/cycle_gan/__init__.py
tinyms/model/cycle_gan/common_net.py
tinyms/model/cycle_gan/cycle_gan.py
tinyms/model/cycle_gan/resnet.py
tinyms/model/cycle_gan/unet.py
tinyms/model/deepfm/__init__.py
tinyms/model/deepfm/deepfm_base_model.py
tinyms/model/deepfm/deepfm_eval_model.py
tinyms/model/deepfm/deepfm_train_model.py
tinyms/optimizers/__init__.py
tinyms/optimizers/bert_optimizer.py
tinyms/serving/__init__.py
tinyms/serving/client/__init__.py
tinyms/serving/client/client.py
tinyms/serving/servable/__init__.py
tinyms-0.3.2.dist-info/LICENSE
tinyms-0.3.2.dist-info/METADATA
tinyms-0.3.2.dist-info/NOTICE
tinyms-0.3.2.dist-info/WHEEL
tinyms-0.3.2.dist-info/top_level.txt
tinyms-0.3.2.dist-info/RECORD
