Metadata-Version: 2.1
Name: tinyms
Version: 0.3.2
Summary: TinyMS is an Easy-to-Use deep learning development toolkit.
Home-page: https://tinyms.readthedocs.io/en/latest/
Author: The TinyMS Authors
Author-email: simple_hlw@163.com
License: Apache 2.0
Download-URL: https://github.com/tinyms-ai/tinyms/tags
Project-URL: Sources, https://github.com/tinyms-ai/tinyms
Project-URL: Issue Tracker, https://github.com/tinyms-ai/tinyms/issues
Keywords: machine learning toolkit
Platform: UNKNOWN
Classifier: Development Status :: 3 - Alpha
Classifier: Environment :: Console
Classifier: Intended Audience :: Developers
Classifier: Intended Audience :: Science/Research
Classifier: License :: OSI Approved :: Apache Software License
Classifier: Operating System :: Microsoft :: Windows
Classifier: Operating System :: POSIX :: Linux
Classifier: Programming Language :: Python :: 3 :: Only
Classifier: Programming Language :: Python :: 3.7
Classifier: Topic :: Scientific/Engineering
Classifier: Topic :: Scientific/Engineering :: Artificial Intelligence
Classifier: Topic :: Software Development
Classifier: Topic :: Software Development :: Libraries
Classifier: Topic :: Software Development :: Libraries :: Python Modules
Requires-Python: >=3.7
Requires-Dist: numpy (>=1.17.0)
Requires-Dist: easydict (>=1.9)
Requires-Dist: scipy (<1.8.0,>=1.5.2)
Requires-Dist: matplotlib (<=3.5.1,>=3.1.3)
Requires-Dist: Pillow (>=6.2.0)
Requires-Dist: mindspore (>=1.6.0)
Requires-Dist: requests (>=2.22.0)
Requires-Dist: flask (==2.0.3)
Requires-Dist: python-Levenshtein (>=0.10.2)
Requires-Dist: gensim (==3.8.1)
Requires-Dist: PyYAML
Requires-Dist: opencv-python (>=4.1.2.30)
Requires-Dist: flask-cors (>=3.0.10)
Requires-Dist: wget (>=3.2)
Requires-Dist: scikit-learn (==1.0.2)
Requires-Dist: tqdm (>=4.62.3)
